songwhip/__init__.py
songwhip/__main__.py
songwhip/__version__.py
songwhip/api.py
songwhip-1.0.dist-info/entry_points.txt
songwhip-1.0.dist-info/LICENSE
songwhip-1.0.dist-info/WHEEL
songwhip-1.0.dist-info/METADATA
songwhip-1.0.dist-info/RECORD
