Metadata-Version: 2.1
Name: songwhip
Version: 1.0
Summary: simple Songwhip client>
Author-email: Amethyst Reese <amethyst@n7.gg>
Requires-Python: >=3.10
Requires-Dist: click >= 8
Requires-Dist: munch >= 2.5
Requires-Dist: rich >= 13
Requires-Dist: attribution==1.6.2 ; extra == "dev"
Requires-Dist: black==23.3.0 ; extra == "dev"
Requires-Dist: flake8==6.0.0 ; extra == "dev"
Requires-Dist: flit==3.8.0 ; extra == "dev"
Requires-Dist: mypy==1.2.0 ; extra == "dev"
Requires-Dist: ufmt==2.0.1 ; extra == "dev"
Requires-Dist: usort==1.0.6 ; extra == "dev"
Project-URL: Home, https://github.com/amyreese/songwhip
Provides-Extra: dev
